.gitignore
reven-0.1.1.dist-info/METADATA
reven-0.1.1.dist-info/WHEEL
reven-0.1.1.dist-info/entry_points.txt
reven-0.1.1.dist-info/licenses/LICENSE
reven/__init__.py
reven/fast/ngram.c
reven/fast/pattern.c
reven/lib.py
reven/main.py
reven/ops/__init__.py
reven/ops/byte_freq.py
reven/ops/hex2bin.py
reven/ops/ngram.py
reven/ops/pattern.py
reven/ops/search.py
reven/ops/slice.py
reven/ops/transform.py
reven/ops/upset.py
reven-0.1.1.dist-info/RECORD
