Metadata-Version: 2.4
Name: reven
Version: 0.1.1
Summary: Flexible reverse engineering CLI tool for analyzing many files at once.
Keywords: reverse engineering
Author-Email: =?utf-8?q?Norbert_Arkadiusz_G=C3=B6rke?= <me@ngorke.dev>, Magnust Hektoen Steensland <mag.steensland@gmail.com>
License-Expression: Apache-2.0
Requires-Dist: attrs~=25.3
Requires-Dist: cattrs~=25.1
Requires-Dist: typer~=0.16.0
Requires-Dist: PyYAML~=6.0
Requires-Dist: dataclass-wizard~=0.35.0
Requires-Dist: scikit-learn~=1.7
Requires-Dist: UpSetPlot~=0.9.0
Requires-Dist: PyQt6~=6.9
